{
  "updateTime": 1771844539105,
  "count": 109,
  "data": [
    {
      "title": "分析，比特币重返 6.6 万美元，Strategy 或迎第 100 次增持，加密概念股盘前企稳",
      "content": "ChainCatcher 消息，据 CoinDesk 报道，在宏观不确定性持续扰动市场之际，比特币反弹并重新站上 66,000 美元关口，加密与相关概念股盘前交易出现企稳迹象，作为全球持有比特币最多的上市公司，Strategy 盘前下跌约 2%，该公司自 2020 年启动比特币财库策略以来或将迎来第 100 次比特币增持。市场情绪指标方面，加密恐惧与贪婪指数跌至 6，刷新阶段低位并已连续七日处于“极度恐惧”区间，不过比特币快速收复部分跌幅，显示低位存在一定抄底需求。",
      "time": "2026-02-23 18:59:49",
      "isImportant": false,
      "isHot": false,
      "isTop": false,
      "link": "https://www.chaincatcher.com/article/2247322",
      "tags": [
        "BTC",
        "市场情绪",
        "抄底需求"
      ],
      "source": "ChainCatcher",
      "sourceColor": "#FF6B35",
      "timestamp": 1771873189000
    },
    {
      "title": "MEXC 即将首发上线 Flying Tulip (FT)",
      "content": "ChainCatcher 消息，MEXC 创新区将于 2026 年 2 月 23 日待满足流动性条件后首发上线 Flying Tulip (FT)，并开放 FT/USDT 和 FT/USDC 交易对。此外，该币种 FT 也即将登陆 MEXC 闪兑，可与其他资产进行无缝、即时兑换。 ",
      "time": "2026-02-23 18:46:08",
      "isImportant": false,
      "isHot": false,
      "isTop": false,
      "link": "https://www.chaincatcher.com/article/2247321",
      "tags": [
        "MEXC",
        "Flying Tulip",
        "FT",
        "交易对"
      ],
      "source": "ChainCatcher",
      "sourceColor": "#FF6B35",
      "timestamp": 1771872368000
    },
    {
      "title": "币安交易所钱包比特币余额升至去年高位，潜在抛压信号升温",
      "content": "ChainCatcher 消息，通常交易所比特币余额上升会被视为潜在抛压信号，意味着投资者可能准备出售资产或将其作为衍生品交易保证金，这两种情况通常都会加剧价格波动。",
      "time": "2026-02-23 18:38:45",
      "isImportant": false,
      "isHot": false,
      "isTop": false,
      "link": "https://www.chaincatcher.com/article/2247320",
      "tags": [
        "比特币",
        "抛压信号",
        "价格波动"
      ],
      "source": "ChainCatcher",
      "sourceColor": "#FF6B35",
      "timestamp": 1771871925000
    },
    {
      "title": "彭博社：曾推动美国比特币 ETF 热潮的对冲基金正迅速撤离，2025 年 Q4 比特币 ETF 持仓环比下降 28%",
      "content": "ChainCatcher 消息，据彭博社报道，曾推动美国比特币交易型基金（ETF）热潮的对冲基金正迅速撤离。根据加密交易平台 Kraken 全资子公司 CF Benchmarks 汇编的数据，规模最大的对冲基金持有的比特币 ETF 总配置下降了 28%。CF Benchmarks 研究主管 Gabe Selby 在 2 月 19 日的一份研究报告中写道：“过去两个季度的主导主题是对冲基金去风险化操作。10 月的冲高回落似乎触发了系统性减仓。”Brevan Howard 大幅调整了其在贝莱德旗下 iShares Bitcoin Trust 中的持仓，成为第四季度该现货 ETF 的最大卖方。其持仓规模下降约 86% 至 550 万股，使其现货头寸价值从约 24 亿美元降至 2.75 亿美元。比特币价格随宏观风险一同下跌，且在某些阶段跌幅甚至更大，这削弱了此前向机构投资者推介的逻辑——即比特币可以对冲通胀、货币贬值或股市压力。",
      "time": "2026-02-23 18:33:14",
      "isImportant": false,
      "isHot": false,
      "isTop": false,
      "link": "https://www.chaincatcher.com/article/2247319",
      "tags": [
        "BTC",
        "对冲基金",
        "ETF"
      ],
      "source": "ChainCatcher",
      "sourceColor": "#FF6B35",
      "timestamp": 1771871594000
    },
    {
      "title": "QCP：比特币跌破 6.5 万美元触发多头清算，矿企去风险化加速但抛压趋于温和",
      "content": "ChainCatcher 消息，QCP Group 发布最新分析指出，比特币今日早盘跌破 65,000 美元，触发约 2.3 亿美元多头清算，市场在消化新一轮关税风险及更广泛地缘政治不确定性之际承压，美国总统特朗普将全球关税从 10% 上调至 15%的举措，进一步加剧宏观风险偏好降温。在比特币价格仍显著低于平均挖矿成本情况下，矿企压力显现，流动性优先于囤币策略，其中 Bitdeer 已清仓其比特币储备，成为矿工去风险化、部分转向 AI 赛道的最新信号。不过，市场并非单边看空，本轮清算连锁反应较今年早些时候明显温和，市场对消息面的反应更为克制。期权市场虽仍对下行风险进行定价，显示仓位结构更加干净，此外 ETF 资金流动更像是基差交易平仓，而非全面撤离，反映资金结构正在调整，而非彻底退出市场。",
      "time": "2026-02-23 18:32:56",
      "isImportant": false,
      "isHot": false,
      "isTop": false,
      "link": "https://www.chaincatcher.com/article/2247318",
      "tags": [
        "BTC",
        "清算",
        "宏观风险"
      ],
      "source": "ChainCatcher",
      "sourceColor": "#FF6B35",
      "timestamp": 1771871576000
    },
    {
      "title": "数据：若 ETH 跌破 1,823 美元，主流 CEX 累计多单清算强度将达 8.91 亿美元",
      "content": "ChainCatcher 消息，据 Coinglass 数据显示，若 ETH 跌破 1,823 美元，主流 CEX 累计多单清算强度将达 8.91 亿美元。反之，若 ETH 突破 2,014 美元，主流 CEX 累计空单清算强度将达 7.22 亿美元。",
      "time": "2026-02-23 18:30:27",
      "isImportant": false,
      "isHot": false,
      "isTop": false,
      "link": "https://www.chaincatcher.com/article/2247317",
      "tags": [
        "清算",
        "ETH"
      ],
      "source": "ChainCatcher",
      "sourceColor": "#FF6B35",
      "timestamp": 1771871427000
    },
    {
      "title": "数据：若 BTC 突破 69,608 美元，主流 CEX 累计空单清算强度将达 12.46 亿美元",
      "content": "ChainCatcher 消息，据 Coinglass 数据显示，若 BTC 突破 69,608 美元，主流 CEX 累计空单清算强度将达 12.46 亿美元。反之，若 BTC 跌破 63,038 美元，主流 CEX 累计多单清算强度将达 11.98 亿美元。",
      "time": "2026-02-23 18:30:25",
      "isImportant": false,
      "isHot": false,
      "isTop": false,
      "link": "https://www.chaincatcher.com/article/2247316",
      "tags": [
        "清算",
        "BTC"
      ],
      "source": "ChainCatcher",
      "sourceColor": "#FF6B35",
      "timestamp": 1771871425000
    },
    {
      "title": "分析：BTC 逼近 “历史平均换手成本” 线，若失守或将进入深熊阶段",
      "content": "ChainCatcher 消息，加密分析师 Murphy 表示，BTC 目前仍在 65,000 美元附近震荡，该位置接近 10y_RP 指标所在区间。该指标在剔除多数已丢失 BTC 成本影响后，被视为更贴近真实水平的 “历史平均换手成本”。该区间或为多头重要心理与成本防线。一旦有效跌破，或意味着本轮下行趋势继续走深熊路径将成为大概率事件。",
      "time": "2026-02-23 18:22:02",
      "isImportant": false,
      "isHot": false,
      "isTop": false,
      "link": "https://www.chaincatcher.com/article/2247315",
      "tags": [
        "BTC",
        "历史平均换手成本",
        "下行趋势"
      ],
      "source": "ChainCatcher",
      "sourceColor": "#FF6B35",
      "timestamp": 1771870922000
    },
    {
      "title": "数据：麻吉大哥加仓以太坊多单并在 1965 - 2050 美元区间挂出 25 笔限价卖单",
      "content": "ChainCatcher 消息，Hyperbot 数据显示，麻吉大哥黄立成刚刚小额加仓其 25 倍杠杆以太坊多单，当前仓位持有约 3300 枚 ETH，浮盈约 10 万美元，清算价约 1878 美元。此外，麻吉大哥还在 1965 美元至 2050 美元区间挂出 25 笔限价卖单，出售数量总计 950 枚 ETH。",
      "time": "2026-02-23 18:10:52",
      "isImportant": false,
      "isHot": false,
      "isTop": false,
      "link": "https://www.chaincatcher.com/article/2247314",
      "tags": [
        "ETH",
        "杠杆交易",
        "限价卖单"
      ],
      "source": "ChainCatcher",
      "sourceColor": "#FF6B35",
      "timestamp": 1771870252000
    },
    {
      "title": "过去 4 小时全网爆仓超 4000 万美元，BTC 爆仓 1779 万美元",
      "content": "ChainCatcher 消息，Coinglass 数据显示，过去 4 小时全网爆仓 42,407,800 美元，多单爆仓 6,211,100 美元，空单爆仓 36,196,700 美元。其中，BTC 爆仓 17,790,000 美元，ETH 爆仓 1,120,000 美元。",
      "time": "2026-02-23 17:45:06",
      "isImportant": false,
      "isHot": false,
      "isTop": false,
      "link": "https://www.chaincatcher.com/article/2247313",
      "tags": [
        "BTC",
        "ETH",
        "爆仓"
      ],
      "source": "ChainCatcher",
      "sourceColor": "#FF6B35",
      "timestamp": 1771868706000
    },
    {
      "title": "10x Research：以太坊进入关键估值区间，Bitmine 巨额浮亏凸显结构性压力",
      "content": "ChainCatcher 消息，加密研究机构 10x Research 在 X 平台发文分析指出，以太坊正处于估值与基本面双重考验的关键阶段，市场需判断其当前低迷是周期性底部，还是面临更深层次的结构性受损。以太坊财库公司 Bitmine 目前承受约 88 亿美元的账面亏损，超过 FTX 崩盘初期客户约 80 亿美元的损失规模，该公司在需求趋弱、ETH 价格接近 2021 年 4 月水平之际大举增持 ETH 也进一步加剧了市场争议。这一对比凸显资本配置结果可能出现的巨大分化，以及时机与治理决策如何决定长期价值创造的最终归属。以太坊当前交易价格已逼近关键估值与成本区间，其核心价值主张正面临结构性检验，投资者需审慎评估以太坊究竟处于周期性低谷，还是正步入更深层的结构性受损阶段。",
      "time": "2026-02-23 17:44:54",
      "isImportant": false,
      "isHot": false,
      "isTop": false,
      "link": "https://www.chaincatcher.com/article/2247312",
      "tags": [
        "ETH",
        "估值",
        "结构性受损"
      ],
      "source": "ChainCatcher",
      "sourceColor": "#FF6B35",
      "timestamp": 1771868694000
    },
    {
      "title": "数据：DGB 24 小时跌超 13%",
      "content": "ChainCatcher 消息，据币安现货数据显示，市场出现大幅波动。DGB 24 小时跌幅达 13.47%，并出现“冲高回落”状态。同时，DUSK 24 小时跌幅 7.47%，同样出现“冲高回落”状态。其余代币如 GALA、IMX、ARB、ZK、ZRO、EIGEN 和 TST 均出现“探底回升”状态，涨幅在 5% 以上。",
      "time": "2026-02-23 17:30:27",
      "isImportant": false,
      "isHot": false,
      "isTop": false,
      "link": "https://www.chaincatcher.com/article/2247311",
      "tags": [
        "DGB",
        "DUSK",
        "市场波动"
      ],
      "source": "ChainCatcher",
      "sourceColor": "#FF6B35",
      "timestamp": 1771867827000
    },
    {
      "title": "币安将于 2 月 24 日对以太坊网络进行钱包维护",
      "content": "ChainCatcher 消息，据官方公告，币安将于 2026 年 02 月 24 日 14:00（东八区时间）对以太坊网络（ETH）进行钱包维护。\n\n为支持此次维护，币安将于 2026 年 02 月 24 日 13:55（东八区时间）暂停对以太坊网络（ETH）的充值、提现业务。维护预计需要 1 小时，维护完成后将自动恢复充值、提现业务。",
      "time": "2026-02-23 17:24:55",
      "isImportant": false,
      "isHot": false,
      "isTop": false,
      "link": "https://www.chaincatcher.com/article/2247310",
      "tags": [
        "币安",
        "钱包维护"
      ],
      "source": "ChainCatcher",
      "sourceColor": "#FF6B35",
      "timestamp": 1771867495000
    },
    {
      "title": "Jane Street 增持 78.5 万枚 MSTR，持仓价值达 1.21 亿美元",
      "content": "ChainCatcher 消息，据 BTCtreasuries 披露，资产管理规模达 6620 亿美元的 Jane Street 披露增持 785,224 枚 MSTR 股票，目前总计持有 951,187 枚 MSTR，持仓价值 1.21 亿美元，仓位增幅达 473%。",
      "time": "2026-02-23 17:08:48",
      "isImportant": false,
      "isHot": false,
      "isTop": false,
      "link": "https://www.chaincatcher.com/article/2247309",
      "tags": [
        "Jane Street",
        "MSTR",
        "资产管理"
      ],
      "source": "ChainCatcher",
      "sourceColor": "#FF6B35",
      "timestamp": 1771866528000
    },
    {
      "title": "数据：某新建钱包从 Bitfinex 提取 500 枚 BTC，约合 3281 万美元",
      "content": "ChainCatcher 消息，据 Onchain Lens 监测，某新建钱包从 Bitfinex 提取 500 枚 BTC，约合 3281 万美元。",
      "time": "2026-02-23 16:57:43",
      "isImportant": false,
      "isHot": false,
      "isTop": false,
      "link": "https://www.chaincatcher.com/article/2247307",
      "tags": [
        "BTC",
        "Bitfinex",
        "新建钱包",
        "链上追踪"
      ],
      "source": "ChainCatcher",
      "sourceColor": "#FF6B35",
      "timestamp": 1771865863000
    },
    {
      "title": "数据：Coinbase 比特币负溢价已持续 39 日，暂报 -0.0405%",
      "content": "ChainCatcher 消息，据 Coinglass 数据显示，Coinbase 比特币溢价指数已连续 39 日处于负溢价，暂报 -0.0405%，超过“1011 崩盘”期间约 30 日的连续负溢价的天数。\n\n自 2026 年以来，该指数仅有 2 个交易日录得正溢价。Coinbase 比特币溢价指数用于衡量 Coinbase 上的比特币价格相对于全球市场平均价格的差异，负溢价通常反映美国市场卖压较大，投资者风险偏好下降，市场避险情绪升温或资金外流。",
      "time": "2026-02-23 16:44:04",
      "isImportant": false,
      "isHot": false,
      "isTop": false,
      "link": "https://www.chaincatcher.com/article/2247306",
      "tags": [
        "Coinbase",
        "BTC",
        "负溢价"
      ],
      "source": "ChainCatcher",
      "sourceColor": "#FF6B35",
      "timestamp": 1771865044000
    },
    {
      "title": "OKX 发布第 40 期 PoR，BTC、ETH、USDT、USDC 总计价值达 268 亿美元",
      "content": "ChainCatcher 消息，据官方消息，OKX 正式发布第 40 期储备金证明（简称 PoR）。本期数据显示，OKX 公示的 22 个主要币种储备金率均达 100%，其中 BTC、ETH、USDT 和 USDC 的储备金率分别为 106%、103%、109% 和 101%，按验证日期价格计算，四项合计储备资产价值达 26,802,436,131 美元。\n\n据悉，OKX 是行业首家达成 POR 连续发布超三年的加密交易所。在此期间，OKX 坚持按月发布 PoR，公示币种数量从 3 个增至 22 个，并接连通过默克尔树、全览默克尔树、以及 zk-STARK 等技术不断升级 PoR 系统，致力于用户资产透明化。",
      "time": "2026-02-23 16:37:44",
      "isImportant": false,
      "isHot": false,
      "isTop": false,
      "link": "https://www.chaincatcher.com/article/2247305",
      "tags": [
        "OKX",
        "PoR",
        "储备金",
        "BTC",
        "ETH"
      ],
      "source": "ChainCatcher",
      "sourceColor": "#FF6B35",
      "timestamp": 1771864664000
    },
    {
      "title": "sUSDD 在 Morpho 上的 TVL 突破 4700 万美元",
      "content": "ChainCatcher 消息，据官方数据，去中心化稳定币 USDD 的生息代币 sUSDD 在去中心化借贷协议 Morpho 上实现快速增长，其 TVL 已突破 4700 万美元。\n\n据悉，在上线仅一个月内，sUSDD/USDT 市场 TVL 就超过了 4000 万美元，并成为收益型稳定币领域第二大 USDT 借贷市场，仅次于 sUSDS。\n\n另外，sUSDD 已集成至 Gauntlet Vaults，借贷需求持续攀升，流动性稳步增强。",
      "time": "2026-02-23 16:34:11",
      "isImportant": false,
      "isHot": false,
      "isTop": false,
      "link": "https://www.chaincatcher.com/article/2247304",
      "tags": [
        "sUSDD",
        "Morpho",
        "去中心化稳定币",
        "借贷市场"
      ],
      "source": "ChainCatcher",
      "sourceColor": "#FF6B35",
      "timestamp": 1771864451000
    },
    {
      "title": "数据：过去 24 小时全网爆仓 4.86 亿美元，多单爆仓 4.35 亿美元，空单爆仓 5,134.15 万美元",
      "content": "ChainCatcher 消息，据 Coinglass 数据，过去 24 小时全网爆仓 4.86 亿美元，多单爆仓 4.35 亿美元，空单爆仓 5,134.15 万美元。其中比特币多单爆仓 2.07 亿美元，比特币空单爆仓 1,954.35 万美元，以太坊多单爆仓 1.09 亿美元，以太坊空单爆仓 846.29 万美元。此外，最近 24 小时，全球共有 139,883 人被爆仓，最大单笔爆仓单发生在 HTX - BTC-USDT 价值 6151.63 万美元。",
      "time": "2026-02-23 16:30:23",
      "isImportant": false,
      "isHot": false,
      "isTop": false,
      "link": "https://www.chaincatcher.com/article/2247303",
      "tags": [
        "全网爆仓",
        "爆仓数据",
        "BTC",
        "ETH"
      ],
      "source": "ChainCatcher",
      "sourceColor": "#FF6B35",
      "timestamp": 1771864223000
    },
    {
      "title": "Bybit 推出限时 USDC 活动 奖池规模 800,000 USDC",
      "content": "ChainCatcher 消息，Bybit 日前推出 USDC 超能出击活动，总奖池高达 800,000 USDC，其中 USDC 储蓄产品年化收益率固定为 6%。\n\n活动现正在进行中，并将于 2026 年 3 月 7 日 11:59（UTC+8）结束。参与用户交易金额达到 500 或以上 USDC 即可瓜分 280,000 USDC奖池。\n\n此外，用户可选购固定收益储蓄，最高质押额达 100,000 USDC，即可获得 6% 固定年化收益率加浮动年化收益率（当前浮动收益率达 41%）。\n\n该活动需要登记，交易金额越高，可共享的奖池比例越大；用户所获年化收益率也随质押金额提高。",
      "time": "2026-02-23 16:30:20",
      "isImportant": false,
      "isHot": false,
      "isTop": false,
      "link": "https://www.chaincatcher.com/article/2247302",
      "tags": [
        "Bybit",
        "USDC"
      ],
      "source": "ChainCatcher",
      "sourceColor": "#FF6B35",
      "timestamp": 1771864220000
    },
    {
      "title": "关于矩阵之门（Matrixport）钱包借贷产品展示升级的通知",
      "link": "https://helpcenter.matrixport.com/zh-CN/articles/12254298-%E5%85%B3%E4%BA%8E%E7%9F%A9%E9%98%B5%E4%B9%8B%E9%97%A8-matrixport-%E9%92%B1%E5%8C%85%E5%80%9F%E8%B4%B7%E4%BA%A7%E5%93%81%E5%B1%95%E7%A4%BA%E5%8D%87%E7%BA%A7%E7%9A%84%E9%80%9A%E7%9F%A5",
      "time": "",
      "source": "Matrixport",
      "sourceColor": "#1e3d59",
      "timestamp": 1771844522672
    },
    {
      "title": "Matrixport美股交易产品正式上线公告",
      "link": "https://helpcenter.matrixport.com/zh-CN/articles/13558154-matrixport%E7%BE%8E%E8%82%A1%E4%BA%A4%E6%98%93%E4%BA%A7%E5%93%81%E6%AD%A3%E5%BC%8F%E4%B8%8A%E7%BA%BF%E5%85%AC%E5%91%8A",
      "time": "",
      "source": "Matrixport",
      "sourceColor": "#1e3d59",
      "timestamp": 1771844522672
    },
    {
      "title": "【网格交易功能下架通知】（2026.1.5）",
      "link": "https://helpcenter.matrixport.com/zh-CN/articles/13233770-%E7%BD%91%E6%A0%BC%E4%BA%A4%E6%98%93%E5%8A%9F%E8%83%BD%E4%B8%8B%E6%9E%B6%E9%80%9A%E7%9F%A5-2026-1-5",
      "time": "",
      "source": "Matrixport",
      "sourceColor": "#1e3d59",
      "timestamp": 1771844522672
    },
    {
      "title": "关于矩阵之门（Matrixport）升级质押借贷服务的通知",
      "link": "https://helpcenter.matrixport.com/zh-CN/articles/13000110-%E5%85%B3%E4%BA%8E%E7%9F%A9%E9%98%B5%E4%B9%8B%E9%97%A8-matrixport-%E5%8D%87%E7%BA%A7%E8%B4%A8%E6%8A%BC%E5%80%9F%E8%B4%B7%E6%9C%8D%E5%8A%A1%E7%9A%84%E9%80%9A%E7%9F%A5",
      "time": "",
      "source": "Matrixport",
      "sourceColor": "#1e3d59",
      "timestamp": 1771844522672
    },
    {
      "title": "Matrixport 合约交易赛获奖名单公示",
      "link": "https://helpcenter.matrixport.com/zh-CN/articles/12307401-matrixport-%E5%90%88%E7%BA%A6%E4%BA%A4%E6%98%93%E8%B5%9B%E8%8E%B7%E5%A5%96%E5%90%8D%E5%8D%95%E5%85%AC%E7%A4%BA",
      "time": "",
      "source": "Matrixport",
      "sourceColor": "#1e3d59",
      "timestamp": 1771844522672
    },
    {
      "title": "关于矩阵之门（Matrixport）财富分体系升级的通知",
      "link": "https://helpcenter.matrixport.com/zh-CN/articles/12231782-%E5%85%B3%E4%BA%8E%E7%9F%A9%E9%98%B5%E4%B9%8B%E9%97%A8-matrixport-%E8%B4%A2%E5%AF%8C%E5%88%86%E4%BD%93%E7%B3%BB%E5%8D%87%E7%BA%A7%E7%9A%84%E9%80%9A%E7%9F%A5",
      "time": "",
      "source": "Matrixport",
      "sourceColor": "#1e3d59",
      "timestamp": 1771844522672
    },
    {
      "title": "矩阵之门（Matrixport）系统更新",
      "link": "https://helpcenter.matrixport.com/zh-CN/articles/11982637-%E7%9F%A9%E9%98%B5%E4%B9%8B%E9%97%A8-matrixport-%E7%B3%BB%E7%BB%9F%E6%9B%B4%E6%96%B0",
      "time": "",
      "source": "Matrixport",
      "sourceColor": "#1e3d59",
      "timestamp": 1771844522672
    },
    {
      "title": "关于矩阵之门（Matrixport ）上线合约双向持仓模式的通知",
      "link": "https://helpcenter.matrixport.com/zh-CN/articles/12007509-%E5%85%B3%E4%BA%8E%E7%9F%A9%E9%98%B5%E4%B9%8B%E9%97%A8-matrixport-%E4%B8%8A%E7%BA%BF%E5%90%88%E7%BA%A6%E5%8F%8C%E5%90%91%E6%8C%81%E4%BB%93%E6%A8%A1%E5%BC%8F%E7%9A%84%E9%80%9A%E7%9F%A5",
      "time": "",
      "source": "Matrixport",
      "sourceColor": "#1e3d59",
      "timestamp": 1771844522672
    },
    {
      "title": "关于矩阵之门（Matrixport）固收产品支持 XAUm 的通知",
      "link": "https://helpcenter.matrixport.com/zh-CN/articles/11949349-%E5%85%B3%E4%BA%8E%E7%9F%A9%E9%98%B5%E4%B9%8B%E9%97%A8-matrixport-%E5%9B%BA%E6%94%B6%E4%BA%A7%E5%93%81%E6%94%AF%E6%8C%81-xaum-%E7%9A%84%E9%80%9A%E7%9F%A5",
      "time": "",
      "source": "Matrixport",
      "sourceColor": "#1e3d59",
      "timestamp": 1771844522672
    },
    {
      "title": "矩阵之门（Matrixport ）合约惊喜活动来袭，最高解锁奖金池达 45,000 USD！",
      "link": "https://helpcenter.matrixport.com/zh-CN/articles/11882183-%E7%9F%A9%E9%98%B5%E4%B9%8B%E9%97%A8-matrixport-%E5%90%88%E7%BA%A6%E6%83%8A%E5%96%9C%E6%B4%BB%E5%8A%A8%E6%9D%A5%E8%A2%AD-%E6%9C%80%E9%AB%98%E8%A7%A3%E9%94%81%E5%A5%96%E9%87%91%E6%B1%A0%E8%BE%BE-45-000-usd",
      "time": "",
      "source": "Matrixport",
      "sourceColor": "#1e3d59",
      "timestamp": 1771844522672
    },
    {
      "title": "关于矩阵之门（Matrixport）活期存系统更新的通知",
      "link": "https://helpcenter.matrixport.com/zh-CN/articles/11938666-%E5%85%B3%E4%BA%8E%E7%9F%A9%E9%98%B5%E4%B9%8B%E9%97%A8-matrixport-%E6%B4%BB%E6%9C%9F%E5%AD%98%E7%B3%BB%E7%BB%9F%E6%9B%B4%E6%96%B0%E7%9A%84%E9%80%9A%E7%9F%A5",
      "time": "",
      "source": "Matrixport",
      "sourceColor": "#1e3d59",
      "timestamp": 1771844522672
    },
    {
      "title": "关于矩阵之门（Matrixport ）上线固收可质押借款功能的通知",
      "link": "https://helpcenter.matrixport.com/zh-CN/articles/11666894-%E5%85%B3%E4%BA%8E%E7%9F%A9%E9%98%B5%E4%B9%8B%E9%97%A8-matrixport-%E4%B8%8A%E7%BA%BF%E5%9B%BA%E6%94%B6%E5%8F%AF%E8%B4%A8%E6%8A%BC%E5%80%9F%E6%AC%BE%E5%8A%9F%E8%83%BD%E7%9A%84%E9%80%9A%E7%9F%A5",
      "time": "",
      "source": "Matrixport",
      "sourceColor": "#1e3d59",
      "timestamp": 1771844522672
    },
    {
      "title": "Matrixport系统升级通知",
      "link": "https://helpcenter.matrixport.com/zh-CN/articles/11743681-matrixport%E7%B3%BB%E7%BB%9F%E5%8D%87%E7%BA%A7%E9%80%9A%E7%9F%A5",
      "time": "",
      "source": "Matrixport",
      "sourceColor": "#1e3d59",
      "timestamp": 1771844522672
    },
    {
      "title": "关于Prime Brokerage系统资金划转机制优化的公告",
      "link": "https://helpcenter.matrixport.com/zh-CN/articles/11666924-%E5%85%B3%E4%BA%8Eprime-brokerage%E7%B3%BB%E7%BB%9F%E8%B5%84%E9%87%91%E5%88%92%E8%BD%AC%E6%9C%BA%E5%88%B6%E4%BC%98%E5%8C%96%E7%9A%84%E5%85%AC%E5%91%8A",
      "time": "",
      "source": "Matrixport",
      "sourceColor": "#1e3d59",
      "timestamp": 1771844522672
    },
    {
      "title": "关于矩阵之门（Matrixport） 上线每日双币产品的通知",
      "link": "https://helpcenter.matrixport.com/zh-CN/articles/11614395-%E5%85%B3%E4%BA%8E%E7%9F%A9%E9%98%B5%E4%B9%8B%E9%97%A8-matrixport-%E4%B8%8A%E7%BA%BF%E6%AF%8F%E6%97%A5%E5%8F%8C%E5%B8%81%E4%BA%A7%E5%93%81%E7%9A%84%E9%80%9A%E7%9F%A5",
      "time": "",
      "source": "Matrixport",
      "sourceColor": "#1e3d59",
      "timestamp": 1771844522672
    },
    {
      "title": "Contact",
      "link": "https://group.hashkey.com/en/news/categories/announcement-1",
      "time": "",
      "source": "HashKey Group",
      "sourceColor": "#121212",
      "timestamp": 1771844509215
    },
    {
      "title": "Announcement",
      "link": "https://group.hashkey.com/en/news/categories/announcement-1",
      "time": "",
      "source": "HashKey Group",
      "sourceColor": "#121212",
      "timestamp": 1771844509215
    },
    {
      "title": "TradePilot 計劃NEW面向精英交易員的跨交易所跟單交易基礎設施",
      "link": "https://www.kucoin.com/zh-hant/announcement/en-kucoin-tradepilot-program-empowering-all-elite-lead-traders",
      "time": "",
      "source": "Kucoin",
      "sourceColor": "#24ae8f",
      "timestamp": 1771844483983
    },
    {
      "title": "統一交易帳戶新上線跨幣種保證金機制，實現資本效益最大化",
      "link": "https://www.kucoin.com/zh-hant/announcement/hk-kucoin-unified-trading-account-uta-launch-announcement",
      "time": "",
      "source": "Kucoin",
      "sourceColor": "#24ae8f",
      "timestamp": 1771844483983
    },
    {
      "title": "公告第一時間獲取 KuCoin 的重要更新和官方新聞",
      "link": "https://www.kucoin.com/zh-hant/announcement",
      "time": "",
      "source": "Kucoin",
      "sourceColor": "#24ae8f",
      "timestamp": 1771844483983
    },
    {
      "title": "公告平台最新公告，包括上新、活动、升级等",
      "link": "https://www.gate.com/zh/announcements",
      "time": "",
      "source": "Gate.io",
      "sourceColor": "#e91e63",
      "timestamp": 1771844476178
    },
    {
      "title": "English",
      "link": "https://www.gate.com/announcements/lastest",
      "time": "",
      "source": "Gate.io",
      "sourceColor": "#e91e63",
      "timestamp": 1771844476178
    },
    {
      "title": "Tiếng Việt",
      "link": "https://www.gate.com/vi/announcements/lastest",
      "time": "",
      "source": "Gate.io",
      "sourceColor": "#e91e63",
      "timestamp": 1771844476178
    },
    {
      "title": "Español",
      "link": "https://www.gate.com/es/announcements/lastest",
      "time": "",
      "source": "Gate.io",
      "sourceColor": "#e91e63",
      "timestamp": 1771844476178
    },
    {
      "title": "Русский",
      "link": "https://www.gate.com/ru/announcements/lastest",
      "time": "",
      "source": "Gate.io",
      "sourceColor": "#e91e63",
      "timestamp": 1771844476178
    },
    {
      "title": "Français (Afrique)",
      "link": "https://www.gate.com/fr/announcements/lastest",
      "time": "",
      "source": "Gate.io",
      "sourceColor": "#e91e63",
      "timestamp": 1771844476178
    },
    {
      "title": "Português (Portugal)",
      "link": "https://www.gate.com/pt/announcements/lastest",
      "time": "",
      "source": "Gate.io",
      "sourceColor": "#e91e63",
      "timestamp": 1771844476178
    },
    {
      "title": "Bahasa Indonesia",
      "link": "https://www.gate.com/id/announcements/lastest",
      "time": "",
      "source": "Gate.io",
      "sourceColor": "#e91e63",
      "timestamp": 1771844476178
    },
    {
      "title": "بالعربية",
      "link": "https://www.gate.com/ar/announcements/lastest",
      "time": "",
      "source": "Gate.io",
      "sourceColor": "#e91e63",
      "timestamp": 1771844476178
    },
    {
      "title": "Українська",
      "link": "https://www.gate.com/uk/announcements/lastest",
      "time": "",
      "source": "Gate.io",
      "sourceColor": "#e91e63",
      "timestamp": 1771844476178
    },
    {
      "title": "Português (Brasil)",
      "link": "https://www.gate.com/pt-br/announcements/lastest",
      "time": "",
      "source": "Gate.io",
      "sourceColor": "#e91e63",
      "timestamp": 1771844476178
    },
    {
      "title": "Gate 双周报",
      "link": "https://www.gate.com/zh/announcements/dau",
      "time": "",
      "source": "Gate.io",
      "sourceColor": "#e91e63",
      "timestamp": 1771844476178
    },
    {
      "title": "Gate 研究院",
      "link": "https://www.gate.com/zh/announcements/gate-learn",
      "time": "",
      "source": "Gate.io",
      "sourceColor": "#e91e63",
      "timestamp": 1771844476178
    },
    {
      "title": "Gate Charity",
      "link": "https://www.gate.com/zh/announcements/charity",
      "time": "",
      "source": "Gate.io",
      "sourceColor": "#e91e63",
      "timestamp": 1771844476178
    },
    {
      "title": "DEX 活动",
      "link": "https://www.gate.com/zh/announcements/web3",
      "time": "",
      "source": "Gate.io",
      "sourceColor": "#e91e63",
      "timestamp": 1771844476178
    },
    {
      "title": "Español (Latinoamérica)",
      "link": "https://www.okx.com/es-la/help/section/announcements-latest-announcements",
      "time": "",
      "source": "OKX",
      "sourceColor": "#000000",
      "timestamp": 1771844464030
    },
    {
      "title": "Français",
      "link": "https://www.okx.com/fr/help/section/announcements-latest-announcements",
      "time": "",
      "source": "OKX",
      "sourceColor": "#000000",
      "timestamp": 1771844464030
    },
    {
      "title": "Português",
      "link": "https://www.okx.com/pt/help/section/announcements-latest-announcements",
      "time": "",
      "source": "OKX",
      "sourceColor": "#000000",
      "timestamp": 1771844464030
    },
    {
      "title": "العربية",
      "link": "https://www.okx.com/ar/help/section/announcements-latest-announcements",
      "time": "",
      "source": "OKX",
      "sourceColor": "#000000",
      "timestamp": 1771844464030
    },
    {
      "title": "Deutsch",
      "link": "https://www.okx.com/de/help/section/announcements-latest-announcements",
      "time": "",
      "source": "OKX",
      "sourceColor": "#000000",
      "timestamp": 1771844464030
    },
    {
      "title": "Español (España)",
      "link": "https://www.okx.com/es-es/help/section/announcements-latest-announcements",
      "time": "",
      "source": "OKX",
      "sourceColor": "#000000",
      "timestamp": 1771844464030
    },
    {
      "title": "Italiano",
      "link": "https://www.okx.com/it/help/section/announcements-latest-announcements",
      "time": "",
      "source": "OKX",
      "sourceColor": "#000000",
      "timestamp": 1771844464030
    },
    {
      "title": "Nederlands",
      "link": "https://www.okx.com/nl/help/section/announcements-latest-announcements",
      "time": "",
      "source": "OKX",
      "sourceColor": "#000000",
      "timestamp": 1771844464030
    },
    {
      "title": "Polski",
      "link": "https://www.okx.com/pl/help/section/announcements-latest-announcements",
      "time": "",
      "source": "OKX",
      "sourceColor": "#000000",
      "timestamp": 1771844464030
    },
    {
      "title": "稳定币金融平台 Rhythmic 完成 400 万美元融资，Dragonfly 等领投",
      "time": "融资",
      "isImportant": false,
      "link": "",
      "source": "Foresight",
      "sourceColor": "#9C27B0",
      "timestamp": 1771844411394
    },
    {
      "title": "月之暗面近 20 日累计收入已超 2025 年全年总收入",
      "time": "数据追踪",
      "isImportant": true,
      "link": "",
      "source": "Foresight",
      "sourceColor": "#9C27B0",
      "timestamp": 1771844411394
    },
    {
      "title": "IoTeX 发布安全事件更新，受影响用户的补偿方案将于 48 小时内公布",
      "time": "重要消息",
      "isImportant": true,
      "link": "",
      "source": "Foresight",
      "sourceColor": "#9C27B0",
      "timestamp": 1771844411394
    },
    {
      "title": "ShapeShift 创始人买入 9911 枚 ETH，价值约 2038 万美元",
      "time": "数据追踪",
      "isImportant": true,
      "link": "",
      "source": "Foresight",
      "sourceColor": "#9C27B0",
      "timestamp": 1771844411394
    },
    {
      "title": "Bitdeer：出售比特币不应引起市场担忧，正在评估多个土地收购机会",
      "time": "重要消息",
      "isImportant": true,
      "link": "",
      "source": "Foresight",
      "sourceColor": "#9C27B0",
      "timestamp": 1771844411394
    },
    {
      "title": "某地址 17 小时内杠杆做多买入 61.93 枚 WBTC，价值约 409 万美元",
      "time": "WBTC",
      "isImportant": false,
      "link": "",
      "source": "Foresight",
      "sourceColor": "#9C27B0",
      "timestamp": 1771844411394
    },
    {
      "title": "Nexira 将推迟 TGE 日期，Ruby 奖励将提升 3 倍",
      "time": "空投",
      "isImportant": false,
      "link": "",
      "source": "Foresight",
      "sourceColor": "#9C27B0",
      "timestamp": 1771844411394
    },
    {
      "title": "某巨鲸 7 小时内出售 9.48 万枚 SOL，价值约 742 万美元",
      "time": "重要消息",
      "isImportant": true,
      "link": "",
      "source": "Foresight",
      "sourceColor": "#9C27B0",
      "timestamp": 1771844411394
    },
    {
      "title": "比特币升破 66000 USDT",
      "time": "行情异动",
      "isImportant": true,
      "link": "",
      "source": "Foresight",
      "sourceColor": "#9C27B0",
      "timestamp": 1771844411394
    },
    {
      "title": "The Smarter Web Company 花费 169 万英镑收购 Squarebird",
      "time": "分享到",
      "isImportant": false,
      "link": "",
      "source": "Foresight",
      "sourceColor": "#9C27B0",
      "timestamp": 1771844411394
    },
    {
      "title": "SOL 现货 ETF 上周净流入 1431 万美元，XRP 现货 ETF 上周净流入 184.46 万美元",
      "time": "信托",
      "isImportant": false,
      "link": "",
      "source": "Foresight",
      "sourceColor": "#9C27B0",
      "timestamp": 1771844411394
    },
    {
      "title": "以太坊现货 ETF 上周净流出 1.23 亿美元，连续 5 周净流出",
      "time": "以太坊",
      "isImportant": false,
      "link": "",
      "source": "Foresight",
      "sourceColor": "#9C27B0",
      "timestamp": 1771844411394
    },
    {
      "title": "比特币现货 ETF 上周净流出 3.16 亿美元，连续 5 周净流出",
      "time": "信托",
      "isImportant": false,
      "link": "",
      "source": "Foresight",
      "sourceColor": "#9C27B0",
      "timestamp": 1771844411394
    },
    {
      "title": "Upbit 将 IoTeX（IOTX）列入交易警示品种",
      "time": "IoTeX",
      "isImportant": false,
      "link": "",
      "source": "Foresight",
      "sourceColor": "#9C27B0",
      "timestamp": 1771844411394
    },
    {
      "title": "Riot Platforms 副总裁：比特币仍是世界上最被低估的资产",
      "time": "比特币",
      "isImportant": false,
      "link": "",
      "source": "Foresight",
      "sourceColor": "#9C27B0",
      "timestamp": 1771844411394
    },
    {
      "title": "glassnode：近期投资者净实现盈亏的 7 日 EMA 今日回升至 -4.8 亿美元 / 日",
      "time": "Glassnode",
      "isImportant": false,
      "link": "",
      "source": "Foresight",
      "sourceColor": "#9C27B0",
      "timestamp": 1771844411394
    },
    {
      "title": "美国或将于 2 月 23 日或 24 日对伊朗发动军事打击",
      "time": "重要消息",
      "isImportant": true,
      "link": "",
      "source": "Foresight",
      "sourceColor": "#9C27B0",
      "timestamp": 1771844411394
    },
    {
      "title": "某交易员 3 日内持续平仓 HYPE 多头头寸，仍持有 4100 万美元做多仓位",
      "time": "DATA",
      "isImportant": false,
      "link": "",
      "source": "Foresight",
      "sourceColor": "#9C27B0",
      "timestamp": 1771844411394
    },
    {
      "title": "Polymarket 上市场押注 USD.AI 上线次日 FDV 超 1.5 亿美元概率为 89%",
      "time": "数据",
      "isImportant": false,
      "link": "",
      "source": "Foresight",
      "sourceColor": "#9C27B0",
      "timestamp": 1771844411394
    },
    {
      "title": "zERC20 推出 zERC20 协议支持资产 zBNB",
      "time": "重要消息",
      "isImportant": true,
      "link": "",
      "source": "Foresight",
      "sourceColor": "#9C27B0",
      "timestamp": 1771844411394
    },
    {
      "title": "Bybit Alpha 及 Byreal 上线 Lobstar",
      "time": "交易所动态",
      "isImportant": true,
      "link": "",
      "source": "Foresight",
      "sourceColor": "#9C27B0",
      "timestamp": 1771844411394
    },
    {
      "title": "Lobstar 市值回升突破 1000 万美元，24 小时涨幅 43.72%",
      "time": "行情异动",
      "isImportant": true,
      "link": "",
      "source": "Foresight",
      "sourceColor": "#9C27B0",
      "timestamp": 1771844411394
    },
    {
      "title": "CoinList 已开放 USD.AI 白名单销售",
      "time": "CoinList",
      "isImportant": false,
      "link": "",
      "source": "Foresight",
      "sourceColor": "#9C27B0",
      "timestamp": 1771844411394
    },
    {
      "title": "AI 代理 Lobstar Wilde 因某用户需「治疗破伤风」，将约 25 万美元代币转入其账户",
      "time": "重要消息",
      "isImportant": true,
      "link": "",
      "source": "Foresight",
      "sourceColor": "#9C27B0",
      "timestamp": 1771844411394
    },
    {
      "title": "密苏里州比特币战略储备基金法案提交至众议院商业委员会审查",
      "time": "比特币",
      "isImportant": false,
      "link": "",
      "source": "Foresight",
      "sourceColor": "#9C27B0",
      "timestamp": 1771844411394
    },
    {
      "title": "Vitalik：安全性与用户体验并非独立领域，目标最小化意图与系统行为偏差",
      "time": "重要消息",
      "isImportant": true,
      "link": "",
      "source": "Foresight",
      "sourceColor": "#9C27B0",
      "timestamp": 1771844411394
    },
    {
      "title": "某地址持有 ETH 超 2 年后抛售 3313 枚，盈利缩窄至 33.8 万美元",
      "time": "ETH",
      "isImportant": false,
      "link": "",
      "source": "Foresight",
      "sourceColor": "#9C27B0",
      "timestamp": 1771844411394
    },
    {
      "title": "数据：过去 24 小时全网爆仓 3.39 亿美元，多单爆仓 3.2 亿美元",
      "time": "数据追踪",
      "isImportant": true,
      "link": "",
      "source": "Foresight",
      "sourceColor": "#9C27B0",
      "timestamp": 1771844411394
    },
    {
      "title": "贾跃亭：未来 AIxC 将专注「RWA 和 EAI 生态」战略",
      "time": "重要消息",
      "isImportant": true,
      "link": "",
      "source": "Foresight",
      "sourceColor": "#9C27B0",
      "timestamp": 1771844411394
    },
    {
      "title": "10:45\n\t\t\t\t\t\t\t\t\t   Binance平台比特币余额昨日升至676,834.84枚，创2024年11月以来新高",
      "time": "",
      "isImportant": false,
      "link": "https://www.theblockbeats.info/flash/333189",
      "source": "BlockBeats",
      "sourceColor": "#1E88E5",
      "timestamp": 1771844404418
    },
    {
      "title": "BlockBeats 消息，2 月 23 日，据 CoinDesk 报道，链上分析平台 CryptoQuant 数据显示，Binance 平台关联钱包的比特币余额在上周日升至 676,834.84 枚（约 445.3 亿美元），为 2024 年 11 月以来最高水平，较去年 11 月多月低点 618,782 枚增长约 9.3%。",
      "time": "",
      "isImportant": false,
      "link": "https://www.theblockbeats.info/inclusionid/?target=https%3A%2F%2Fwww.coindesk.com%2Fmarkets%2F2026%2F02%2F23%2Fbitcoin-balances-on-binance-hit-highest-since-november-2024-here-s-what-it-means",
      "source": "BlockBeats",
      "sourceColor": "#1E88E5",
      "timestamp": 1771844404418
    },
    {
      "title": "10:31\n\t\t\t\t\t\t\t\t\t   彭博社：曾推动美国比特币ETF热潮的对冲基金正迅速撤离，2025年Q4比特币ETF持仓环比下降28%",
      "time": "",
      "isImportant": false,
      "link": "https://www.theblockbeats.info/flash/333188",
      "source": "BlockBeats",
      "sourceColor": "#1E88E5",
      "timestamp": 1771844404418
    },
    {
      "title": "BlockBeats 消息，2 月 23 日，据彭博社报道，曾推动美国比特币交易型基金（ETF）热潮的对冲基金正迅速撤离。根据加密交易平台 Kraken 全资子公司 CF Benchmarks 汇编的数据，2025 年第三季度至第四季度期间，规模最大的对冲基金持有的比特币 ETF 总配置下降了 28%。",
      "time": "",
      "isImportant": false,
      "link": "https://www.theblockbeats.info/inclusionid/?target=https%3A%2F%2Fwww.bloomberg.com%2Fnews%2Farticles%2F2026-02-23%2Fhedge-funds-that-piled-into-us-bitcoin-btc-funds-are-first-to-exit",
      "source": "BlockBeats",
      "sourceColor": "#1E88E5",
      "timestamp": 1771844404418
    },
    {
      "title": "10:21\n\t\t\t\t\t\t\t\t\t   分析：BTC逼近「历史平均换手成本」线，若失守或将进入深熊阶段",
      "time": "",
      "isImportant": false,
      "link": "https://www.theblockbeats.info/flash/333187",
      "source": "BlockBeats",
      "sourceColor": "#1E88E5",
      "timestamp": 1771844404418
    },
    {
      "title": "BlockBeats 消息，2 月 23 日，加密分析师 Murphy 表示，BTC 目前仍在 65,000 美元附近震荡，该位置接近 <10y_RP 指标所在区间。该指标在剔除多数已丢失 BTC 成本影响后，被视为更贴近真实水平的「历史平均换手成本」。",
      "time": "",
      "isImportant": false,
      "link": "https://www.theblockbeats.info/inclusionid/?target=https%3A%2F%2Fx.com%2FMurphychen888%2Fstatus%2F2025873473005093341",
      "source": "BlockBeats",
      "sourceColor": "#1E88E5",
      "timestamp": 1771844404418
    },
    {
      "title": "09:48\n\t\t\t\t\t\t\t\t\t   月之暗面近20日收入已超2025年全年总收入",
      "time": "",
      "isImportant": false,
      "link": "https://www.theblockbeats.info/flash/333186",
      "source": "BlockBeats",
      "sourceColor": "#1E88E5",
      "timestamp": 1771844404418
    },
    {
      "title": "BlockBeats 消息，2 月 23 日，据澎湃新闻报道，从多个知情人士处获悉，月之暗面（Kimi）旗下 K2.5 大模型发布不到一个月，Kimi 近 20 天累计收入已超过 2025 年全年总收入，增长主要受全球付费用户及 API 调用量大涨共同驱动，特别是海外付费用户保持高速增长，Kimi 海外收入已超国内。",
      "time": "",
      "isImportant": false,
      "link": "https://www.theblockbeats.info/inclusionid/?target=https%3A%2F%2Fwww.thepaper.cn%2FnewsDetail_forward_32636837",
      "source": "BlockBeats",
      "sourceColor": "#1E88E5",
      "timestamp": 1771844404418
    },
    {
      "title": "09:16\n\t\t\t\t\t\t\t\t\t   美股盘前加密概念股普跌，BitMine跌3.33%",
      "time": "",
      "isImportant": false,
      "link": "https://www.theblockbeats.info/flash/333185",
      "source": "BlockBeats",
      "sourceColor": "#1E88E5",
      "timestamp": 1771844404418
    },
    {
      "title": "BlockBeats 消息，2 月 23 日，据 Bitget 行情数据，比特币日内一度跌破 6.5 万美元，美股盘前加密概念股普跌，其中：BitMine 跌 3.33%、SharpLink 跌 2.68%、Strategy 跌 2.24%、Coinbase 跌 1.81%、Circle 跌 1.27%。",
      "time": "",
      "isImportant": false,
      "link": "http://service.weibo.com/share/share.php?url=https://m.theblockbeats.info/flash/179978&sharesource=weibo&title=%E7%BE%8E%E8%82%A1%E7%9B%98%E5%89%8D%E5%8A%A0%E5%AF%86%E6%A6%82%E5%BF%B5%E8%82%A1%E6%99%AE%E8%B7%8C%EF%BC%8CBitMine%E8%B7%8C3.33%&pic=https://image.blockbeats.cn/other/mob/favlogo.png&appkey=1533649352",
      "source": "BlockBeats",
      "sourceColor": "#1E88E5",
      "timestamp": 1771844404418
    },
    {
      "title": "09:04\n\t\t\t\t\t\t\t\t\t   Binance将于2月24日14:00对以太坊网络（ETH）进行钱包维护",
      "time": "",
      "isImportant": false,
      "link": "https://www.theblockbeats.info/flash/333184",
      "source": "BlockBeats",
      "sourceColor": "#1E88E5",
      "timestamp": 1771844404418
    },
    {
      "title": "BlockBeats 消息，2 月 23 日，据官方消息，Binance 将于 2026 年 02 月 24 日 14:00（东八区时间）对以太坊网络（ETH）进行钱包维护。为支持此次维护，Binance 将于 2026 年 02 月 24 日 13:55（东八区时间）暂停对以太坊网络（ETH）的充值、提现业务。维护预计需要 1 小时，维护完成后将自动恢复充值、提现业务。",
      "time": "",
      "isImportant": false,
      "link": "http://service.weibo.com/share/share.php?url=https://m.theblockbeats.info/flash/179977&sharesource=weibo&title=Binance%E5%B0%86%E4%BA%8E2%E6%9C%8824%E6%97%A514:00%E5%AF%B9%E4%BB%A5%E5%A4%AA%E5%9D%8A%E7%BD%91%E7%BB%9C%EF%BC%88ETH%EF%BC%89%E8%BF%9B%E8%A1%8C%E9%92%B1%E5%8C%85%E7%BB%B4%E6%8A%A4&pic=https://image.blockbeats.cn/other/mob/favlogo.png&appkey=1533649352",
      "source": "BlockBeats",
      "sourceColor": "#1E88E5",
      "timestamp": 1771844404418
    },
    {
      "title": "08:55\n\t\t\t\t\t\t\t\t\t   某新建钱包从Bitfinex提取500枚BTC",
      "time": "",
      "isImportant": false,
      "link": "https://www.theblockbeats.info/flash/333183",
      "source": "BlockBeats",
      "sourceColor": "#1E88E5",
      "timestamp": 1771844404418
    },
    {
      "title": "BlockBeats 消息，2 月 23 日，据 Onchain Lens 监测，某新建钱包从 Bitfinex 提取 500 枚 BTC，价值约合 3281 万美元。",
      "time": "",
      "isImportant": false,
      "link": "https://www.theblockbeats.info/inclusionid/?target=https%3A%2F%2Fx.com%2FOnchainLens%2Fstatus%2F2025856881571557827",
      "source": "BlockBeats",
      "sourceColor": "#1E88E5",
      "timestamp": 1771844404418
    },
    {
      "title": "08:54\n\t\t\t\t\t\t\t\t\t   Pump.fun已累计回购价值超3亿美元PUMP代币",
      "time": "",
      "isImportant": false,
      "link": "https://www.theblockbeats.info/flash/333182",
      "source": "BlockBeats",
      "sourceColor": "#1E88E5",
      "timestamp": 1771844404418
    },
    {
      "title": "BlockBeats 消息，2 月 23 日，据 fees.pump.fun 数据显示，Pump.fun 昨日花费 14,649.99 枚 SOL（约 124.86 万美元）回购 6.016 亿枚 PUMP。",
      "time": "",
      "isImportant": false,
      "link": "https://www.theblockbeats.info/inclusionid/?target=https%3A%2F%2Ffees.pump.fun%2F",
      "source": "BlockBeats",
      "sourceColor": "#1E88E5",
      "timestamp": 1771844404418
    }
  ]
}